alfred/__init__.py
alfred/symbols.py
alfred/visitor.py
flake8_alfred/__init__.py
flake8_alfred/symbols.py
flake8_alfred/visitor.py
flake8_alfred-1.1.1.dist-info/METADATA
flake8_alfred-1.1.1.dist-info/RECORD
flake8_alfred-1.1.1.dist-info/WHEEL
flake8_alfred-1.1.1.dist-info/entry_points.txt
flake8_alfred-1.1.1.dist-info/top_level.txt
