Metadata-Version: 2.1
Name: flake8-alfred
Version: 1.1.1
Summary: Flake8 plugin warning for unsafe functions
Home-page: UNKNOWN
Author: Alexis Pierru
Author-email: ap@datatheorem.com
License: UNKNOWN
Platform: UNKNOWN
Classifier: Development Status :: 5 - Production/Stable
Classifier: Programming Language :: Python :: 3.6
Requires-Python: >=3.6
Requires-Dist: flake8
